{
  "partition": {
    "index": 1219,
    "name": "aes_cipher_top.input90.A",
    "inbits": {
      "key": [
        65
      ]
    },
    "outbits": {
      "input90.A": [
        0
      ]
    },
    "crossbits": {}
  },
  "gold_module": {
    "name": "gold.aes_cipher_top.input90.A",
    "internal": {
      "_16553_.A2": [
        0
      ]
    },
    "unused": {},
    "cellcount": 2,
    "bitcount": 3
  },
  "gate_module": {
    "name": "gold.aes_cipher_top.input90.A",
    "internal": {
      "_16553_.A2": [
        0
      ]
    },
    "unused": {},
    "cellcount": 2,
    "bitcount": 3
  }
}
