{
  "partition": {
    "index": 612,
    "name": "aes_cipher_top.text_out.71",
    "inbits": {
      "output356.Y": [
        0
      ]
    },
    "outbits": {
      "text_out": [
        71
      ]
    },
    "crossbits": {}
  },
  "gold_module": {
    "name": "gold.aes_cipher_top.text_out.71",
    "internal": {},
    "unused": {},
    "cellcount": 1,
    "bitcount": 2
  },
  "gate_module": {
    "name": "gold.aes_cipher_top.text_out.71",
    "internal": {},
    "unused": {},
    "cellcount": 1,
    "bitcount": 2
  }
}
