{
  "partition": {
    "index": 1390,
    "name": "aes_cipher_top.input245.Y",
    "inbits": {
      "input245.A": [
        0
      ]
    },
    "outbits": {
      "input245.Y": [
        0
      ]
    },
    "crossbits": {}
  },
  "gold_module": {
    "name": "gold.aes_cipher_top.input245.Y",
    "internal": {},
    "unused": {},
    "cellcount": 1,
    "bitcount": 2
  },
  "gate_module": {
    "name": "gold.aes_cipher_top.input245.Y",
    "internal": {},
    "unused": {},
    "cellcount": 1,
    "bitcount": 2
  }
}
