{
  "level_0": {
    "0": {
      "54": {
        "boxes": [
          0,
          0,
          0,
          0
        ]
      },
      "163": {
        "boxes": [
          0,
          0,
          0,
          0
        ]
      },
      "238": {
        "boxes": [
          0,
          0,
          0,
          0
        ]
      },
      "287": {
        "boxes": [
          0,
          0,
          0,
          0
        ]
      },
      "335": {
        "boxes": [
          0,
          0,
          0,
          0
        ]
      },
      "356": {
        "boxes": [
          0,
          0,
          0,
          0
        ]
      },
      "440": {
        "boxes": [
          0,
          0,
          0,
          0
        ]
      },
      "467": {
        "boxes": [
          0,
          0,
          0,
          0
        ]
      }
    },
    "1": {
      "55": {
        "boxes": [
          0,
          0,
          0,
          0
        ]
      },
      "62": {
        "boxes": [
          0,
          0,
          0,
          0
        ]
      },
      "167": {
        "boxes": [
          0,
          0,
          0,
          0
        ]
      },
      "463": {
        "boxes": [
          0,
          0,
          0,
          0
        ]
      }
    },
    "2": {
      "60": {
        "boxes": [
          0,
          0,
          0,
          0
        ]
      },
      "149": {
        "boxes": [
          0,
          0,
          0,
          0
        ]
      },
      "155": {
        "boxes": [
          0,
          0,
          0,
          0
        ]
      },
      "472": {
        "boxes": [
          0,
          0,
          0,
          0
        ]
      },
      "481": {
        "boxes": [
          0,
          0,
          0,
          0
        ]
      }
    },
    "3": {
      "56": {
        "boxes": [
          0,
          0,
          0,
          0
        ]
      },
      "173": {
        "boxes": [
          0,
          0,
          0,
          0
        ]
      },
      "218": {
        "boxes": [
          0,
          0,
          0,
          0
        ]
      },
      "519": {
        "boxes": [
          0,
          0,
          0,
          0
        ]
      }
    },
    "4": {
      "61": {
        "boxes": [
          0,
          0,
          0,
          0
        ]
      },
      "143": {
        "boxes": [
          0,
          0,
          0,
          0
        ]
      },
      "145": {
        "boxes": [
          0,
          0,
          0,
          0
        ]
      },
      "307": {
        "boxes": [
          0,
          0,
          0,
          0
        ]
      },
      "477": {
        "boxes": [
          0,
          0,
          0,
          0
        ]
      }
    },
    "5": {
      "57": {
        "boxes": [
          0,
          0,
          0,
          0
        ]
      },
      "69": {
        "boxes": [
          0,
          0,
          0,
          0
        ]
      },
      "114": {
        "boxes": [
          0,
          0,
          0,
          0
        ]
      },
      "178": {
        "boxes": [
          0,
          0,
          0,
          0
        ]
      },
      "228": {
        "boxes": [
          0,
          0,
          0,
          0
        ]
      },
      "341": {
        "boxes": [
          0,
          0,
          0,
          0
        ]
      },
      "511": {
        "boxes": [
          0,
          0,
          0,
          0
        ]
      },
      "515": {
        "boxes": [
          0,
          0,
          0,
          0
        ]
      }
    },
    "6": {
      "58": {
        "boxes": [
          0,
          0,
          0,
          0
        ]
      },
      "171": {
        "boxes": [
          0,
          0,
          0,
          0
        ]
      },
      "172": {
        "boxes": [
          0,
          0,
          0,
          0
        ]
      },
      "176": {
        "boxes": [
          0,
          0,
          0,
          0
        ]
      },
      "177": {
        "boxes": [
          0,
          0,
          0,
          0
        ]
      },
      "435": {
        "boxes": [
          0,
          0,
          0,
          0
        ]
      },
      "517": {
        "boxes": [
          0,
          0,
          0,
          0
        ]
      },
      "521": {
        "boxes": [
          0,
          0,
          0,
          0
        ]
      }
    },
    "7": {
      "59": {
        "boxes": [
          0,
          0,
          0,
          0
        ]
      },
      "63": {
        "boxes": [
          0,
          0,
          0,
          0
        ]
      },
      "158": {
        "boxes": [
          0,
          0,
          0,
          0
        ]
      },
      "196": {
        "boxes": [
          0,
          0,
          0,
          0
        ]
      },
      "373": {
        "boxes": [
          0,
          0,
          0,
          0
        ]
      },
      "479": {
        "boxes": [
          0,
          0,
          0,
          0
        ]
      },
      "484": {
        "boxes": [
          4,
          9,
          14,
          18
        ]
      },
      "486": {
        "boxes": [
          0,
          0,
          0,
          0
        ]
      }
    },
    "8": {
      "64": {
        "boxes": [
          0,
          0,
          0,
          0
        ]
      },
      "101": {
        "boxes": [
          0,
          0,
          0,
          0
        ]
      },
      "132": {
        "boxes": [
          0,
          0,
          0,
          0
        ]
      },
      "495": {
        "boxes": [
          0,
          0,
          0,
          0
        ]
      }
    },
    "9": {
      "183": {
        "boxes": [
          0,
          0,
          0,
          0
        ]
      },
      "193": {
        "boxes": [
          0,
          0,
          0,
          0
        ]
      },
      "290": {
        "boxes": [
          0,
          0,
          0,
          0
        ]
      },
      "291": {
        "boxes": [
          0,
          0,
          0,
          0
        ]
      },
      "293": {
        "boxes": [
          0,
          0,
          0,
          0
        ]
      }
    },
    "10": {
      "65": {
        "boxes": [
          0,
          0,
          0,
          0
        ]
      },
      "71": {
        "boxes": [
          0,
          0,
          0,
          0
        ]
      },
      "105": {
        "boxes": [
          0,
          0,
          0,
          0
        ]
      },
      "124": {
        "boxes": [
          0,
          0,
          0,
          0
        ]
      },
      "491": {
        "boxes": [
          0,
          0,
          0,
          0
        ]
      },
      "503": {
        "boxes": [
          0,
          0,
          0,
          0
        ]
      }
    },
    "11": {
      "66": {
        "boxes": [
          0,
          0,
          0,
          0
        ]
      },
      "207": {
        "boxes": [
          0,
          0,
          0,
          0
        ]
      },
      "379": {
        "boxes": [
          0,
          0,
          0,
          0
        ]
      },
      "489": {
        "boxes": [
          0,
          0,
          0,
          0
        ]
      }
    },
    "12": {
      "95": {
        "boxes": [
          0,
          0,
          0,
          0
        ]
      },
      "97": {
        "boxes": [
          0,
          0,
          0,
          0
        ]
      },
      "240": {
        "boxes": [
          0,
          0,
          0,
          0
        ]
      },
      "381": {
        "boxes": [
          0,
          0,
          0,
          0
        ]
      },
      "487": {
        "boxes": [
          4,
          0,
          14,
          9
        ]
      }
    },
    "13": {
      "68": {
        "boxes": [
          0,
          0,
          0,
          0
        ]
      },
      "386": {
        "boxes": [
          0,
          0,
          0,
          0
        ]
      },
      "393": {
        "boxes": [
          0,
          0,
          0,
          0
        ]
      },
      "497": {
        "boxes": [
          0,
          0,
          0,
          0
        ]
      }
    },
    "14": {
      "103": {
        "boxes": [
          0,
          0,
          0,
          0
        ]
      },
      "104": {
        "boxes": [
          0,
          0,
          0,
          0
        ]
      },
      "243": {
        "boxes": [
          0,
          0,
          0,
          0
        ]
      },
      "388": {
        "boxes": [
          0,
          0,
          0,
          0
        ]
      },
      "493": {
        "boxes": [
          0,
          0,
          0,
          0
        ]
      }
    },
    "15": {
      "70": {
        "boxes": [
          0,
          0,
          0,
          0
        ]
      },
      "119": {
        "boxes": [
          0,
          0,
          0,
          0
        ]
      },
      "507": {
        "boxes": [
          0,
          0,
          0,
          0
        ]
      }
    },
    "16": {
      "72": {
        "boxes": [
          0,
          0,
          0,
          0
        ]
      },
      "128": {
        "boxes": [
          0,
          0,
          0,
          0
        ]
      },
      "137": {
        "boxes": [
          0,
          0,
          0,
          0
        ]
      },
      "499": {
        "boxes": [
          0,
          0,
          0,
          0
        ]
      }
    },
    "17": {
      "102": {
        "boxes": [
          0,
          0,
          0,
          0
        ]
      },
      "106": {
        "boxes": [
          0,
          0,
          0,
          0
        ]
      },
      "110": {
        "boxes": [
          0,
          0,
          0,
          0
        ]
      },
      "244": {
        "boxes": [
          0,
          0,
          0,
          0
        ]
      },
      "256": {
        "boxes": [
          0,
          0,
          0,
          0
        ]
      }
    },
    "18": {
      "73": {
        "boxes": [
          0,
          0,
          0,
          0
        ]
      },
      "113": {
        "boxes": [
          0,
          0,
          0,
          0
        ]
      },
      "115": {
        "boxes": [
          0,
          0,
          0,
          0
        ]
      },
      "117": {
        "boxes": [
          0,
          0,
          0,
          0
        ]
      },
      "417": {
        "boxes": [
          0,
          0,
          0,
          0
        ]
      },
      "426": {
        "boxes": [
          0,
          0,
          0,
          0
        ]
      },
      "509": {
        "boxes": [
          0,
          0,
          0,
          0
        ]
      },
      "513": {
        "boxes": [
          0,
          0,
          0,
          0
        ]
      }
    },
    "19": {
      "76": {
        "boxes": [
          0,
          0,
          0,
          0
        ]
      },
      "78": {
        "boxes": [
          9,
          4,
          18,
          14
        ]
      },
      "83": {
        "boxes": [
          9,
          4,
          18,
          14
        ]
      },
      "202": {
        "boxes": [
          0,
          0,
          0,
          0
        ]
      },
      "203": {
        "boxes": [
          9,
          4,
          18,
          14
        ]
      },
      "204": {
        "boxes": [
          0,
          0,
          0,
          0
        ]
      },
      "216": {
        "boxes": [
          0,
          0,
          0,
          0
        ]
      },
      "231": {
        "boxes": [
          0,
          0,
          0,
          0
        ]
      }
    },
    "20": {
      "77": {
        "boxes": [
          9,
          4,
          18,
          14
        ]
      },
      "81": {
        "boxes": [
          9,
          4,
          18,
          14
        ]
      },
      "82": {
        "boxes": [
          9,
          4,
          18,
          14
        ]
      },
      "89": {
        "boxes": [
          9,
          4,
          18,
          14
        ]
      },
      "90": {
        "boxes": [
          0,
          0,
          0,
          0
        ]
      }
    },
    "21": {
      "263": {
        "boxes": [
          0,
          0,
          0,
          0
        ]
      },
      "274": {
        "boxes": [
          0,
          0,
          0,
          0
        ]
      },
      "310": {
        "boxes": [
          0,
          0,
          0,
          0
        ]
      },
      "321": {
        "boxes": [
          0,
          0,
          0,
          0
        ]
      }
    },
    "22": {
      "79": {
        "boxes": [
          0,
          0,
          0,
          0
        ]
      },
      "84": {
        "boxes": [
          9,
          4,
          18,
          14
        ]
      },
      "86": {
        "boxes": [
          0,
          0,
          0,
          0
        ]
      },
      "208": {
        "boxes": [
          0,
          0,
          0,
          0
        ]
      },
      "211": {
        "boxes": [
          0,
          0,
          0,
          0
        ]
      }
    },
    "23": {
      "85": {
        "boxes": [
          9,
          4,
          18,
          14
        ]
      },
      "91": {
        "boxes": [
          0,
          0,
          0,
          0
        ]
      },
      "92": {
        "boxes": [
          0,
          0,
          0,
          0
        ]
      },
      "206": {
        "boxes": [
          0,
          0,
          0,
          0
        ]
      }
    },
    "24": {
      "93": {
        "boxes": [
          4,
          0,
          14,
          9
        ]
      },
      "96": {
        "boxes": [
          0,
          0,
          0,
          0
        ]
      },
      "213": {
        "boxes": [
          0,
          0,
          0,
          0
        ]
      },
      "458": {
        "boxes": [
          9,
          4,
          18,
          14
        ]
      },
      "461": {
        "boxes": [
          0,
          0,
          0,
          0
        ]
      }
    },
    "25": {
      "99": {
        "boxes": [
          0,
          0,
          0,
          0
        ]
      },
      "100": {
        "boxes": [
          0,
          0,
          0,
          0
        ]
      },
      "109": {
        "boxes": [
          0,
          0,
          0,
          0
        ]
      },
      "395": {
        "boxes": [
          0,
          0,
          0,
          0
        ]
      }
    },
    "26": {
      "98": {
        "boxes": [
          0,
          0,
          0,
          0
        ]
      },
      "139": {
        "boxes": [
          0,
          0,
          0,
          0
        ]
      },
      "220": {
        "boxes": [
          0,
          0,
          0,
          0
        ]
      },
      "241": {
        "boxes": [
          0,
          0,
          0,
          0
        ]
      },
      "289": {
        "boxes": [
          0,
          0,
          0,
          0
        ]
      }
    },
    "27": {
      "135": {
        "boxes": [
          0,
          0,
          0,
          0
        ]
      },
      "182": {
        "boxes": [
          0,
          0,
          0,
          0
        ]
      },
      "187": {
        "boxes": [
          0,
          0,
          0,
          0
        ]
      },
      "227": {
        "boxes": [
          0,
          0,
          0,
          0
        ]
      }
    },
    "28": {
      "107": {
        "boxes": [
          0,
          0,
          0,
          0
        ]
      },
      "239": {
        "boxes": [
          0,
          0,
          0,
          0
        ]
      },
      "245": {
        "boxes": [
          0,
          0,
          0,
          0
        ]
      },
      "248": {
        "boxes": [
          0,
          0,
          0,
          0
        ]
      },
      "252": {
        "boxes": [
          0,
          0,
          0,
          0
        ]
      },
      "313": {
        "boxes": [
          0,
          0,
          0,
          0
        ]
      },
      "391": {
        "boxes": [
          4,
          0,
          14,
          9
        ]
      },
      "445": {
        "boxes": [
          0,
          0,
          0,
          0
        ]
      }
    },
    "29": {
      "108": {
        "boxes": [
          0,
          0,
          0,
          0
        ]
      },
      "111": {
        "boxes": [
          0,
          0,
          0,
          0
        ]
      },
      "131": {
        "boxes": [
          0,
          0,
          0,
          0
        ]
      },
      "140": {
        "boxes": [
          0,
          0,
          0,
          0
        ]
      },
      "219": {
        "boxes": [
          0,
          0,
          0,
          0
        ]
      },
      "222": {
        "boxes": [
          0,
          0,
          0,
          0
        ]
      },
      "288": {
        "boxes": [
          0,
          0,
          0,
          0
        ]
      },
      "384": {
        "boxes": [
          4,
          0,
          14,
          9
        ]
      }
    },
    "30": {
      "116": {
        "boxes": [
          0,
          0,
          0,
          0
        ]
      },
      "134": {
        "boxes": [
          0,
          0,
          0,
          0
        ]
      },
      "179": {
        "boxes": [
          0,
          0,
          0,
          0
        ]
      },
      "272": {
        "boxes": [
          0,
          0,
          0,
          0
        ]
      },
      "273": {
        "boxes": [
          0,
          0,
          0,
          0
        ]
      }
    },
    "31": {
      "174": {
        "boxes": [
          0,
          0,
          0,
          0
        ]
      },
      "185": {
        "boxes": [
          0,
          0,
          0,
          0
        ]
      },
      "186": {
        "boxes": [
          0,
          0,
          0,
          0
        ]
      },
      "270": {
        "boxes": [
          0,
          0,
          0,
          0
        ]
      }
    },
    "32": {
      "118": {
        "boxes": [
          0,
          0,
          0,
          0
        ]
      },
      "212": {
        "boxes": [
          0,
          0,
          0,
          0
        ]
      },
      "402": {
        "boxes": [
          0,
          0,
          0,
          0
        ]
      },
      "412": {
        "boxes": [
          0,
          0,
          0,
          0
        ]
      },
      "419": {
        "boxes": [
          0,
          0,
          0,
          0
        ]
      },
      "428": {
        "boxes": [
          0,
          0,
          0,
          0
        ]
      },
      "437": {
        "boxes": [
          0,
          0,
          0,
          0
        ]
      },
      "453": {
        "boxes": [
          0,
          0,
          0,
          0
        ]
      }
    },
    "33": {
      "120": {
        "boxes": [
          0,
          0,
          0,
          0
        ]
      },
      "133": {
        "boxes": [
          0,
          0,
          0,
          0
        ]
      },
      "136": {
        "boxes": [
          0,
          0,
          0,
          0
        ]
      },
      "253": {
        "boxes": [
          0,
          0,
          0,
          0
        ]
      },
      "254": {
        "boxes": [
          0,
          0,
          0,
          0
        ]
      }
    },
    "34": {
      "125": {
        "boxes": [
          0,
          0,
          0,
          0
        ]
      },
      "129": {
        "boxes": [
          0,
          0,
          0,
          0
        ]
      },
      "138": {
        "boxes": [
          0,
          0,
          0,
          0
        ]
      },
      "257": {
        "boxes": [
          0,
          0,
          0,
          0
        ]
      }
    },
    "35": {
      "121": {
        "boxes": [
          0,
          0,
          0,
          0
        ]
      },
      "264": {
        "boxes": [
          0,
          0,
          0,
          0
        ]
      },
      "269": {
        "boxes": [
          0,
          0,
          0,
          0
        ]
      },
      "275": {
        "boxes": [
          0,
          0,
          0,
          0
        ]
      },
      "359": {
        "boxes": [
          0,
          0,
          0,
          0
        ]
      },
      "360": {
        "boxes": [
          0,
          0,
          0,
          0
        ]
      },
      "361": {
        "boxes": [
          0,
          0,
          0,
          0
        ]
      },
      "422": {
        "boxes": [
          0,
          0,
          0,
          0
        ]
      }
    },
    "36": {
      "122": {
        "boxes": [
          0,
          0,
          0,
          0
        ]
      },
      "123": {
        "boxes": [
          0,
          0,
          0,
          0
        ]
      },
      "126": {
        "boxes": [
          0,
          0,
          0,
          0
        ]
      },
      "127": {
        "boxes": [
          0,
          0,
          0,
          0
        ]
      },
      "400": {
        "boxes": [
          0,
          0,
          0,
          0
        ]
      },
      "410": {
        "boxes": [
          0,
          0,
          0,
          0
        ]
      },
      "501": {
        "boxes": [
          0,
          0,
          0,
          0
        ]
      },
      "505": {
        "boxes": [
          0,
          0,
          0,
          0
        ]
      }
    },
    "37": {
      "130": {
        "boxes": [
          0,
          0,
          0,
          0
        ]
      },
      "226": {
        "boxes": [
          0,
          0,
          0,
          0
        ]
      },
      "249": {
        "boxes": [
          0,
          0,
          0,
          0
        ]
      },
      "315": {
        "boxes": [
          0,
          0,
          0,
          0
        ]
      },
      "338": {
        "boxes": [
          0,
          0,
          0,
          0
        ]
      },
      "405": {
        "boxes": [
          0,
          0,
          0,
          0
        ]
      },
      "406": {
        "boxes": [
          0,
          0,
          0,
          0
        ]
      },
      "415": {
        "boxes": [
          0,
          4,
          9,
          14
        ]
      }
    },
    "38": {
      "141": {
        "boxes": [
          0,
          0,
          0,
          0
        ]
      },
      "181": {
        "boxes": [
          0,
          0,
          0,
          0
        ]
      },
      "224": {
        "boxes": [
          0,
          0,
          0,
          0
        ]
      },
      "260": {
        "boxes": [
          0,
          0,
          0,
          0
        ]
      },
      "262": {
        "boxes": [
          0,
          0,
          0,
          0
        ]
      },
      "265": {
        "boxes": [
          0,
          0,
          0,
          0
        ]
      },
      "423": {
        "boxes": [
          0,
          0,
          0,
          0
        ]
      },
      "432": {
        "boxes": [
          0,
          0,
          0,
          0
        ]
      }
    },
    "39": {
      "142": {
        "boxes": [
          0,
          0,
          0,
          0
        ]
      },
      "164": {
        "boxes": [
          0,
          0,
          0,
          0
        ]
      },
      "168": {
        "boxes": [
          0,
          0,
          0,
          0
        ]
      },
      "189": {
        "boxes": [
          0,
          0,
          0,
          0
        ]
      },
      "190": {
        "boxes": [
          0,
          0,
          0,
          0
        ]
      },
      "191": {
        "boxes": [
          0,
          0,
          0,
          0
        ]
      },
      "271": {
        "boxes": [
          0,
          0,
          0,
          0
        ]
      },
      "332": {
        "boxes": [
          0,
          0,
          0,
          0
        ]
      }
    },
    "40": {
      "144": {
        "boxes": [
          0,
          0,
          0,
          0
        ]
      },
      "146": {
        "boxes": [
          0,
          0,
          0,
          0
        ]
      },
      "147": {
        "boxes": [
          0,
          0,
          0,
          0
        ]
      },
      "151": {
        "boxes": [
          0,
          0,
          0,
          0
        ]
      },
      "194": {
        "boxes": [
          0,
          0,
          0,
          0
        ]
      },
      "318": {
        "boxes": [
          0,
          0,
          0,
          0
        ]
      },
      "319": {
        "boxes": [
          0,
          0,
          0,
          0
        ]
      },
      "326": {
        "boxes": [
          0,
          0,
          0,
          0
        ]
      }
    },
    "41": {
      "148": {
        "boxes": [
          0,
          0,
          0,
          0
        ]
      },
      "150": {
        "boxes": [
          0,
          0,
          0,
          0
        ]
      },
      "153": {
        "boxes": [
          0,
          0,
          0,
          0
        ]
      },
      "154": {
        "boxes": [
          0,
          0,
          0,
          0
        ]
      },
      "304": {
        "boxes": [
          0,
          0,
          0,
          0
        ]
      },
      "353": {
        "boxes": [
          0,
          0,
          0,
          0
        ]
      },
      "474": {
        "boxes": [
          0,
          0,
          0,
          0
        ]
      },
      "483": {
        "boxes": [
          0,
          0,
          0,
          0
        ]
      }
    },
    "42": {
      "152": {
        "boxes": [
          0,
          0,
          0,
          0
        ]
      },
      "170": {
        "boxes": [
          0,
          0,
          0,
          0
        ]
      },
      "188": {
        "boxes": [
          0,
          0,
          0,
          0
        ]
      },
      "297": {
        "boxes": [
          0,
          0,
          0,
          0
        ]
      },
      "298": {
        "boxes": [
          0,
          0,
          0,
          0
        ]
      },
      "325": {
        "boxes": [
          0,
          0,
          0,
          0
        ]
      },
      "327": {
        "boxes": [
          0,
          0,
          0,
          0
        ]
      },
      "336": {
        "boxes": [
          0,
          0,
          0,
          0
        ]
      }
    },
    "43": {
      "156": {
        "boxes": [
          0,
          0,
          0,
          0
        ]
      },
      "157": {
        "boxes": [
          0,
          0,
          0,
          0
        ]
      },
      "198": {
        "boxes": [
          0,
          0,
          0,
          0
        ]
      },
      "346": {
        "boxes": [
          0,
          0,
          0,
          0
        ]
      },
      "347": {
        "boxes": [
          0,
          0,
          0,
          0
        ]
      },
      "357": {
        "boxes": [
          0,
          0,
          0,
          0
        ]
      },
      "362": {
        "boxes": [
          0,
          0,
          0,
          0
        ]
      },
      "367": {
        "boxes": [
          0,
          0,
          0,
          0
        ]
      }
    },
    "44": {
      "159": {
        "boxes": [
          0,
          0,
          0,
          0
        ]
      },
      "197": {
        "boxes": [
          0,
          0,
          0,
          0
        ]
      },
      "366": {
        "boxes": [
          0,
          0,
          0,
          0
        ]
      },
      "368": {
        "boxes": [
          0,
          0,
          0,
          0
        ]
      }
    },
    "45": {
      "247": {
        "boxes": [
          0,
          0,
          0,
          0
        ]
      },
      "294": {
        "boxes": [
          0,
          0,
          0,
          0
        ]
      },
      "339": {
        "boxes": [
          0,
          0,
          0,
          0
        ]
      },
      "348": {
        "boxes": [
          0,
          0,
          0,
          0
        ]
      },
      "398": {
        "boxes": [
          4,
          0,
          14,
          9
        ]
      }
    },
    "46": {
      "160": {
        "boxes": [
          0,
          0,
          0,
          0
        ]
      },
      "192": {
        "boxes": [
          0,
          0,
          0,
          0
        ]
      },
      "195": {
        "boxes": [
          0,
          0,
          0,
          0
        ]
      },
      "342": {
        "boxes": [
          0,
          0,
          0,
          0
        ]
      },
      "343": {
        "boxes": [
          0,
          0,
          0,
          0
        ]
      }
    },
    "47": {
      "161": {
        "boxes": [
          0,
          0,
          0,
          0
        ]
      },
      "162": {
        "boxes": [
          0,
          0,
          0,
          0
        ]
      },
      "165": {
        "boxes": [
          0,
          0,
          0,
          0
        ]
      },
      "166": {
        "boxes": [
          0,
          0,
          0,
          0
        ]
      },
      "235": {
        "boxes": [
          0,
          0,
          0,
          0
        ]
      },
      "284": {
        "boxes": [
          0,
          0,
          0,
          0
        ]
      },
      "465": {
        "boxes": [
          0,
          0,
          0,
          0
        ]
      },
      "469": {
        "boxes": [
          0,
          0,
          0,
          0
        ]
      }
    },
    "48": {
      "169": {
        "boxes": [
          0,
          0,
          0,
          0
        ]
      },
      "230": {
        "boxes": [
          4,
          9,
          14,
          18
        ]
      },
      "261": {
        "boxes": [
          0,
          0,
          0,
          0
        ]
      },
      "277": {
        "boxes": [
          0,
          0,
          0,
          0
        ]
      },
      "278": {
        "boxes": [
          0,
          0,
          0,
          0
        ]
      },
      "296": {
        "boxes": [
          0,
          0,
          0,
          0
        ]
      },
      "299": {
        "boxes": [
          0,
          0,
          0,
          0
        ]
      },
      "308": {
        "boxes": [
          0,
          0,
          0,
          0
        ]
      }
    },
    "49": {
      "175": {
        "boxes": [
          0,
          0,
          0,
          0
        ]
      },
      "401": {
        "boxes": [
          0,
          0,
          0,
          0
        ]
      },
      "411": {
        "boxes": [
          0,
          0,
          0,
          0
        ]
      },
      "449": {
        "boxes": [
          4,
          0,
          14,
          9
        ]
      }
    },
    "50": {
      "209": {
        "boxes": [
          0,
          0,
          0,
          0
        ]
      },
      "418": {
        "boxes": [
          0,
          0,
          0,
          0
        ]
      },
      "427": {
        "boxes": [
          0,
          0,
          0,
          0
        ]
      },
      "436": {
        "boxes": [
          0,
          0,
          0,
          0
        ]
      },
      "452": {
        "boxes": [
          0,
          0,
          0,
          0
        ]
      }
    },
    "51": {
      "180": {
        "boxes": [
          0,
          0,
          0,
          0
        ]
      },
      "184": {
        "boxes": [
          0,
          0,
          0,
          0
        ]
      },
      "217": {
        "boxes": [
          0,
          0,
          0,
          0
        ]
      },
      "225": {
        "boxes": [
          0,
          0,
          0,
          0
        ]
      },
      "337": {
        "boxes": [
          0,
          0,
          0,
          0
        ]
      },
      "340": {
        "boxes": [
          0,
          0,
          0,
          0
        ]
      },
      "431": {
        "boxes": [
          0,
          0,
          0,
          0
        ]
      },
      "456": {
        "boxes": [
          0,
          0,
          0,
          0
        ]
      }
    },
    "52": {
      "232": {
        "boxes": [
          4,
          9,
          14,
          18
        ]
      },
      "281": {
        "boxes": [
          4,
          9,
          14,
          18
        ]
      },
      "301": {
        "boxes": [
          4,
          9,
          14,
          18
        ]
      },
      "329": {
        "boxes": [
          4,
          9,
          14,
          18
        ]
      },
      "350": {
        "boxes": [
          4,
          9,
          14,
          18
        ]
      },
      "370": {
        "boxes": [
          4,
          9,
          14,
          18
        ]
      },
      "450": {
        "boxes": [
          4,
          0,
          14,
          9
        ]
      }
    },
    "53": {
      "242": {
        "boxes": [
          0,
          0,
          0,
          0
        ]
      },
      "312": {
        "boxes": [
          0,
          0,
          0,
          0
        ]
      },
      "317": {
        "boxes": [
          0,
          0,
          0,
          0
        ]
      },
      "376": {
        "boxes": [
          0,
          0,
          0,
          0
        ]
      },
      "441": {
        "boxes": [
          0,
          0,
          0,
          0
        ]
      },
      "443": {
        "boxes": [
          0,
          0,
          0,
          0
        ]
      },
      "444": {
        "boxes": [
          0,
          0,
          0,
          0
        ]
      },
      "447": {
        "boxes": [
          0,
          0,
          0,
          0
        ]
      }
    },
    "54": {
      "250": {
        "boxes": [
          0,
          0,
          0,
          0
        ]
      },
      "259": {
        "boxes": [
          0,
          0,
          0,
          0
        ]
      },
      "457": {
        "boxes": [
          0,
          0,
          0,
          0
        ]
      },
      "460": {
        "boxes": [
          0,
          0,
          0,
          0
        ]
      },
      "475": {
        "boxes": [
          0,
          0,
          0,
          0
        ]
      },
      "516": {
        "boxes": [
          0,
          0,
          0,
          0
        ]
      },
      "520": {
        "boxes": [
          0,
          0,
          0,
          0
        ]
      }
    },
    "55": {
      "251": {
        "boxes": [
          0,
          0,
          0,
          0
        ]
      },
      "255": {
        "boxes": [
          0,
          0,
          0,
          0
        ]
      },
      "266": {
        "boxes": [
          0,
          0,
          0,
          0
        ]
      },
      "276": {
        "boxes": [
          0,
          0,
          0,
          0
        ]
      },
      "279": {
        "boxes": [
          0,
          0,
          0,
          0
        ]
      },
      "311": {
        "boxes": [
          0,
          0,
          0,
          0
        ]
      },
      "316": {
        "boxes": [
          0,
          0,
          0,
          0
        ]
      },
      "442": {
        "boxes": [
          0,
          0,
          0,
          0
        ]
      }
    },
    "56": {
      "258": {
        "boxes": [
          0,
          0,
          0,
          0
        ]
      },
      "309": {
        "boxes": [
          0,
          0,
          0,
          0
        ]
      },
      "314": {
        "boxes": [
          0,
          0,
          0,
          0
        ]
      },
      "322": {
        "boxes": [
          0,
          0,
          0,
          0
        ]
      },
      "358": {
        "boxes": [
          0,
          0,
          0,
          0
        ]
      },
      "363": {
        "boxes": [
          0,
          0,
          0,
          0
        ]
      },
      "407": {
        "boxes": [
          0,
          0,
          0,
          0
        ]
      },
      "446": {
        "boxes": [
          0,
          0,
          0,
          0
        ]
      }
    },
    "57": {
      "67": {
        "boxes": [
          0,
          0,
          0,
          0
        ]
      },
      "300": {
        "boxes": [
          4,
          9,
          14,
          18
        ]
      },
      "305": {
        "boxes": [
          9,
          4,
          18,
          14
        ]
      },
      "306": {
        "boxes": [
          0,
          0,
          0,
          0
        ]
      },
      "328": {
        "boxes": [
          4,
          9,
          14,
          18
        ]
      },
      "333": {
        "boxes": [
          9,
          4,
          18,
          14
        ]
      },
      "377": {
        "boxes": [
          4,
          0,
          14,
          9
        ]
      },
      "424": {
        "boxes": [
          0,
          4,
          9,
          14
        ]
      }
    },
    "58": {
      "74": {
        "boxes": [
          0,
          0,
          0,
          0
        ]
      },
      "75": {
        "boxes": [
          0,
          0,
          0,
          0
        ]
      },
      "215": {
        "boxes": [
          0,
          0,
          0,
          0
        ]
      },
      "221": {
        "boxes": [
          0,
          0,
          0,
          0
        ]
      },
      "351": {
        "boxes": [
          0,
          0,
          0,
          0
        ]
      },
      "375": {
        "boxes": [
          0,
          0,
          0,
          0
        ]
      },
      "404": {
        "boxes": [
          0,
          0,
          0,
          0
        ]
      }
    },
    "59": {
      "80": {
        "boxes": [
          0,
          0,
          0,
          0
        ]
      },
      "451": {
        "boxes": [
          0,
          0,
          0,
          0
        ]
      },
      "471": {
        "boxes": [
          0,
          0,
          0,
          0
        ]
      },
      "502": {
        "boxes": [
          4,
          0,
          14,
          9
        ]
      },
      "506": {
        "boxes": [
          0,
          4,
          9,
          14
        ]
      },
      "510": {
        "boxes": [
          0,
          4,
          9,
          14
        ]
      },
      "514": {
        "boxes": [
          0,
          4,
          9,
          14
        ]
      },
      "518": {
        "boxes": [
          9,
          4,
          18,
          14
        ]
      }
    },
    "60": {
      "87": {
        "boxes": [
          0,
          0,
          0,
          0
        ]
      },
      "462": {
        "boxes": [
          9,
          4,
          18,
          14
        ]
      },
      "466": {
        "boxes": [
          4,
          9,
          14,
          18
        ]
      },
      "470": {
        "boxes": [
          9,
          4,
          18,
          14
        ]
      },
      "480": {
        "boxes": [
          4,
          9,
          14,
          18
        ]
      }
    },
    "61": {
      "476": {
        "boxes": [
          4,
          9,
          14,
          18
        ]
      },
      "490": {
        "boxes": [
          4,
          0,
          14,
          9
        ]
      },
      "494": {
        "boxes": [
          4,
          0,
          14,
          9
        ]
      },
      "498": {
        "boxes": [
          4,
          0,
          14,
          9
        ]
      }
    },
    "62": {
      "88": {
        "boxes": [
          0,
          0,
          0,
          0
        ]
      },
      "214": {
        "boxes": [
          9,
          4,
          18,
          14
        ]
      },
      "236": {
        "boxes": [
          9,
          4,
          18,
          14
        ]
      },
      "285": {
        "boxes": [
          9,
          4,
          18,
          14
        ]
      },
      "354": {
        "boxes": [
          4,
          9,
          14,
          18
        ]
      },
      "374": {
        "boxes": [
          4,
          9,
          14,
          18
        ]
      },
      "382": {
        "boxes": [
          9,
          4,
          18,
          14
        ]
      },
      "389": {
        "boxes": [
          4,
          0,
          14,
          9
        ]
      }
    },
    "63": {
      "94": {
        "boxes": [
          0,
          0,
          0,
          0
        ]
      },
      "199": {
        "boxes": [
          0,
          0,
          0,
          0
        ]
      },
      "286": {
        "boxes": [
          0,
          0,
          0,
          0
        ]
      },
      "365": {
        "boxes": [
          0,
          0,
          0,
          0
        ]
      },
      "371": {
        "boxes": [
          0,
          0,
          0,
          0
        ]
      }
    },
    "64": {
      "302": {
        "boxes": [
          0,
          0,
          0,
          0
        ]
      },
      "323": {
        "boxes": [
          0,
          0,
          0,
          0
        ]
      },
      "355": {
        "boxes": [
          0,
          0,
          0,
          0
        ]
      },
      "369": {
        "boxes": [
          4,
          9,
          14,
          18
        ]
      }
    },
    "65": {
      "112": {
        "boxes": [
          0,
          0,
          0,
          0
        ]
      },
      "229": {
        "boxes": [
          0,
          0,
          0,
          0
        ]
      },
      "237": {
        "boxes": [
          0,
          0,
          0,
          0
        ]
      },
      "344": {
        "boxes": [
          0,
          0,
          0,
          0
        ]
      },
      "459": {
        "boxes": [
          0,
          0,
          0,
          0
        ]
      },
      "464": {
        "boxes": [
          0,
          0,
          0,
          0
        ]
      },
      "468": {
        "boxes": [
          0,
          0,
          0,
          0
        ]
      },
      "473": {
        "boxes": [
          0,
          0,
          0,
          0
        ]
      }
    },
    "66": {
      "200": {
        "boxes": [
          0,
          0,
          0,
          0
        ]
      },
      "201": {
        "boxes": [
          0,
          0,
          0,
          0
        ]
      },
      "223": {
        "boxes": [
          0,
          0,
          0,
          0
        ]
      },
      "233": {
        "boxes": [
          0,
          0,
          0,
          0
        ]
      },
      "295": {
        "boxes": [
          0,
          0,
          0,
          0
        ]
      },
      "330": {
        "boxes": [
          0,
          0,
          0,
          0
        ]
      },
      "334": {
        "boxes": [
          0,
          0,
          0,
          0
        ]
      },
      "414": {
        "boxes": [
          0,
          0,
          0,
          0
        ]
      }
    },
    "67": {
      "205": {
        "boxes": [
          4,
          0,
          14,
          9
        ]
      },
      "378": {
        "boxes": [
          4,
          0,
          14,
          9
        ]
      },
      "385": {
        "boxes": [
          4,
          0,
          14,
          9
        ]
      },
      "392": {
        "boxes": [
          4,
          0,
          14,
          9
        ]
      },
      "409": {
        "boxes": [
          4,
          0,
          14,
          9
        ]
      }
    },
    "68": {
      "399": {
        "boxes": [
          4,
          0,
          14,
          9
        ]
      },
      "416": {
        "boxes": [
          0,
          4,
          9,
          14
        ]
      },
      "425": {
        "boxes": [
          0,
          4,
          9,
          14
        ]
      },
      "434": {
        "boxes": [
          0,
          4,
          9,
          14
        ]
      }
    },
    "69": {
      "210": {
        "boxes": [
          0,
          0,
          0,
          0
        ]
      },
      "234": {
        "boxes": [
          0,
          0,
          0,
          0
        ]
      },
      "283": {
        "boxes": [
          0,
          0,
          0,
          0
        ]
      },
      "303": {
        "boxes": [
          0,
          0,
          0,
          0
        ]
      },
      "331": {
        "boxes": [
          0,
          0,
          0,
          0
        ]
      },
      "352": {
        "boxes": [
          0,
          0,
          0,
          0
        ]
      },
      "372": {
        "boxes": [
          0,
          0,
          0,
          0
        ]
      },
      "394": {
        "boxes": [
          0,
          0,
          0,
          0
        ]
      }
    },
    "70": {
      "246": {
        "boxes": [
          0,
          0,
          0,
          0
        ]
      },
      "267": {
        "boxes": [
          0,
          0,
          0,
          0
        ]
      },
      "320": {
        "boxes": [
          0,
          0,
          0,
          0
        ]
      },
      "345": {
        "boxes": [
          0,
          0,
          0,
          0
        ]
      },
      "364": {
        "boxes": [
          0,
          0,
          0,
          0
        ]
      },
      "380": {
        "boxes": [
          0,
          0,
          0,
          0
        ]
      },
      "387": {
        "boxes": [
          0,
          0,
          0,
          0
        ]
      },
      "390": {
        "boxes": [
          0,
          0,
          0,
          0
        ]
      }
    },
    "71": {
      "268": {
        "boxes": [
          0,
          0,
          0,
          0
        ]
      },
      "282": {
        "boxes": [
          0,
          0,
          0,
          0
        ]
      },
      "292": {
        "boxes": [
          0,
          0,
          0,
          0
        ]
      },
      "349": {
        "boxes": [
          4,
          9,
          14,
          18
        ]
      },
      "397": {
        "boxes": [
          0,
          0,
          0,
          0
        ]
      },
      "433": {
        "boxes": [
          0,
          4,
          9,
          14
        ]
      },
      "439": {
        "boxes": [
          0,
          0,
          0,
          0
        ]
      },
      "448": {
        "boxes": [
          0,
          0,
          0,
          0
        ]
      }
    },
    "72": {
      "280": {
        "boxes": [
          4,
          9,
          14,
          18
        ]
      },
      "324": {
        "boxes": [
          0,
          0,
          0,
          0
        ]
      },
      "383": {
        "boxes": [
          0,
          0,
          0,
          0
        ]
      },
      "408": {
        "boxes": [
          4,
          0,
          14,
          9
        ]
      },
      "421": {
        "boxes": [
          0,
          0,
          0,
          0
        ]
      },
      "430": {
        "boxes": [
          0,
          0,
          0,
          0
        ]
      },
      "455": {
        "boxes": [
          0,
          0,
          0,
          0
        ]
      }
    },
    "73": {
      "396": {
        "boxes": [
          4,
          0,
          14,
          9
        ]
      },
      "403": {
        "boxes": [
          4,
          0,
          14,
          9
        ]
      },
      "413": {
        "boxes": [
          0,
          4,
          9,
          14
        ]
      },
      "420": {
        "boxes": [
          0,
          4,
          9,
          14
        ]
      },
      "429": {
        "boxes": [
          0,
          4,
          9,
          14
        ]
      },
      "438": {
        "boxes": [
          0,
          4,
          9,
          14
        ]
      },
      "454": {
        "boxes": [
          4,
          0,
          14,
          9
        ]
      }
    },
    "74": {
      "478": {
        "boxes": [
          0,
          0,
          0,
          0
        ]
      },
      "492": {
        "boxes": [
          0,
          0,
          0,
          0
        ]
      },
      "496": {
        "boxes": [
          0,
          0,
          0,
          0
        ]
      },
      "508": {
        "boxes": [
          0,
          0,
          0,
          0
        ]
      },
      "512": {
        "boxes": [
          0,
          0,
          0,
          0
        ]
      }
    },
    "75": {
      "482": {
        "boxes": [
          0,
          0,
          0,
          0
        ]
      },
      "485": {
        "boxes": [
          0,
          0,
          0,
          0
        ]
      },
      "488": {
        "boxes": [
          0,
          0,
          0,
          0
        ]
      },
      "500": {
        "boxes": [
          0,
          0,
          0,
          0
        ]
      }
    },
    "76": {
      "504": {
        "boxes": [
          0,
          0,
          0,
          0
        ]
      },
      "524": {
        "boxes": [
          0,
          4,
          9,
          14
        ]
      },
      "525": {
        "boxes": [
          0,
          4,
          9,
          14
        ]
      },
      "536": {
        "boxes": [
          0,
          4,
          9,
          14
        ]
      }
    },
    "77": {
      "543": {
        "boxes": [
          0,
          4,
          9,
          14
        ]
      },
      "546": {
        "boxes": [
          0,
          4,
          9,
          14
        ]
      },
      "551": {
        "boxes": [
          0,
          4,
          9,
          14
        ]
      },
      "552": {
        "boxes": [
          0,
          4,
          9,
          14
        ]
      },
      "556": {
        "boxes": [
          0,
          4,
          9,
          14
        ]
      }
    },
    "78": {
      "522": {
        "boxes": [
          9,
          4,
          18,
          14
        ]
      },
      "526": {
        "boxes": [
          0,
          4,
          9,
          14
        ]
      },
      "527": {
        "boxes": [
          0,
          4,
          9,
          14
        ]
      },
      "528": {
        "boxes": [
          0,
          4,
          9,
          14
        ]
      },
      "539": {
        "boxes": [
          0,
          4,
          9,
          14
        ]
      }
    },
    "79": {
      "533": {
        "boxes": [
          0,
          4,
          9,
          14
        ]
      },
      "553": {
        "boxes": [
          0,
          4,
          9,
          14
        ]
      },
      "554": {
        "boxes": [
          0,
          4,
          9,
          14
        ]
      },
      "555": {
        "boxes": [
          0,
          4,
          9,
          14
        ]
      }
    },
    "80": {
      "523": {
        "boxes": [
          0,
          4,
          9,
          14
        ]
      },
      "534": {
        "boxes": [
          0,
          4,
          9,
          14
        ]
      },
      "542": {
        "boxes": [
          0,
          4,
          9,
          14
        ]
      },
      "544": {
        "boxes": [
          0,
          4,
          9,
          14
        ]
      }
    },
    "81": {
      "535": {
        "boxes": [
          0,
          4,
          9,
          14
        ]
      },
      "538": {
        "boxes": [
          0,
          4,
          9,
          14
        ]
      },
      "540": {
        "boxes": [
          0,
          4,
          9,
          14
        ]
      },
      "541": {
        "boxes": [
          0,
          4,
          9,
          14
        ]
      },
      "549": {
        "boxes": [
          0,
          4,
          9,
          14
        ]
      }
    },
    "82": {
      "529": {
        "boxes": [
          0,
          4,
          9,
          14
        ]
      },
      "530": {
        "boxes": [
          0,
          4,
          9,
          14
        ]
      },
      "531": {
        "boxes": [
          0,
          4,
          9,
          14
        ]
      },
      "532": {
        "boxes": [
          0,
          4,
          9,
          14
        ]
      },
      "545": {
        "boxes": [
          0,
          4,
          9,
          14
        ]
      }
    },
    "83": {
      "537": {
        "boxes": [
          0,
          4,
          9,
          14
        ]
      },
      "547": {
        "boxes": [
          0,
          4,
          9,
          14
        ]
      },
      "548": {
        "boxes": [
          0,
          4,
          9,
          14
        ]
      },
      "550": {
        "boxes": [
          0,
          4,
          9,
          14
        ]
      }
    }
  },
  "level_1": {
    "0": {
      "L1_N0": {
        "boxes": [
          0,
          0,
          0,
          0
        ]
      },
      "L1_N73": {
        "boxes": [
          0,
          0,
          0,
          0
        ]
      },
      "L1_N74": {
        "boxes": [
          0,
          0,
          0,
          0
        ]
      },
      "L1_N75": {
        "boxes": [
          0,
          0,
          0,
          0
        ]
      },
      "L1_N76": {
        "boxes": [
          9,
          4,
          18,
          14
        ]
      },
      "L1_N82": {
        "boxes": [
          9,
          4,
          18,
          14
        ]
      },
      "L1_N83": {
        "boxes": [
          9,
          4,
          18,
          14
        ]
      },
      "L1_N9": {
        "boxes": [
          0,
          0,
          0,
          0
        ]
      }
    },
    "1": {
      "L1_N1": {
        "boxes": [
          0,
          0,
          0,
          0
        ]
      },
      "L1_N10": {
        "boxes": [
          0,
          0,
          0,
          0
        ]
      },
      "L1_N16": {
        "boxes": [
          0,
          0,
          0,
          0
        ]
      },
      "L1_N23": {
        "boxes": [
          0,
          0,
          0,
          0
        ]
      },
      "L1_N60": {
        "boxes": [
          0,
          0,
          0,
          0
        ]
      },
      "L1_N63": {
        "boxes": [
          4,
          9,
          14,
          18
        ]
      },
      "L1_N70": {
        "boxes": [
          0,
          0,
          0,
          0
        ]
      },
      "L1_N71": {
        "boxes": [
          0,
          0,
          0,
          0
        ]
      }
    },
    "2": {
      "L1_N11": {
        "boxes": [
          0,
          0,
          0,
          0
        ]
      },
      "L1_N12": {
        "boxes": [
          0,
          0,
          0,
          0
        ]
      },
      "L1_N14": {
        "boxes": [
          0,
          0,
          0,
          0
        ]
      },
      "L1_N56": {
        "boxes": [
          0,
          0,
          0,
          0
        ]
      },
      "L1_N57": {
        "boxes": [
          0,
          0,
          0,
          0
        ]
      },
      "L1_N59": {
        "boxes": [
          4,
          9,
          14,
          18
        ]
      },
      "L1_N61": {
        "boxes": [
          0,
          0,
          0,
          0
        ]
      },
      "L1_N78": {
        "boxes": [
          9,
          4,
          18,
          14
        ]
      }
    },
    "3": {
      "L1_N13": {
        "boxes": [
          0,
          0,
          0,
          0
        ]
      },
      "L1_N2": {
        "boxes": [
          0,
          0,
          0,
          0
        ]
      },
      "L1_N30": {
        "boxes": [
          0,
          0,
          0,
          0
        ]
      },
      "L1_N34": {
        "boxes": [
          0,
          0,
          0,
          0
        ]
      },
      "L1_N42": {
        "boxes": [
          0,
          0,
          0,
          0
        ]
      }
    },
    "4": {
      "L1_N31": {
        "boxes": [
          0,
          0,
          0,
          0
        ]
      },
      "L1_N32": {
        "boxes": [
          0,
          0,
          0,
          0
        ]
      },
      "L1_N33": {
        "boxes": [
          0,
          0,
          0,
          0
        ]
      },
      "L1_N4": {
        "boxes": [
          0,
          0,
          0,
          0
        ]
      }
    },
    "5": {
      "L1_N15": {
        "boxes": [
          0,
          0,
          0,
          0
        ]
      },
      "L1_N17": {
        "boxes": [
          0,
          0,
          0,
          0
        ]
      },
      "L1_N18": {
        "boxes": [
          0,
          0,
          0,
          0
        ]
      },
      "L1_N20": {
        "boxes": [
          0,
          0,
          0,
          0
        ]
      },
      "L1_N3": {
        "boxes": [
          0,
          0,
          0,
          0
        ]
      },
      "L1_N7": {
        "boxes": [
          0,
          0,
          0,
          0
        ]
      },
      "L1_N79": {
        "boxes": [
          9,
          4,
          18,
          14
        ]
      },
      "L1_N80": {
        "boxes": [
          3,
          4,
          12,
          13
        ]
      }
    },
    "6": {
      "L1_N19": {
        "boxes": [
          0,
          0,
          0,
          0
        ]
      },
      "L1_N25": {
        "boxes": [
          0,
          0,
          0,
          0
        ]
      },
      "L1_N26": {
        "boxes": [
          0,
          0,
          0,
          0
        ]
      },
      "L1_N5": {
        "boxes": [
          0,
          0,
          0,
          0
        ]
      },
      "L1_N51": {
        "boxes": [
          0,
          0,
          0,
          0
        ]
      },
      "L1_N52": {
        "boxes": [
          0,
          0,
          0,
          0
        ]
      },
      "L1_N54": {
        "boxes": [
          0,
          0,
          0,
          0
        ]
      },
      "L1_N81": {
        "boxes": [
          9,
          4,
          18,
          14
        ]
      }
    },
    "7": {
      "L1_N21": {
        "boxes": [
          0,
          0,
          0,
          0
        ]
      },
      "L1_N29": {
        "boxes": [
          0,
          0,
          0,
          0
        ]
      },
      "L1_N35": {
        "boxes": [
          0,
          0,
          0,
          0
        ]
      },
      "L1_N64": {
        "boxes": [
          0,
          0,
          0,
          0
        ]
      },
      "L1_N72": {
        "boxes": [
          0,
          0,
          0,
          0
        ]
      }
    },
    "8": {
      "L1_N43": {
        "boxes": [
          0,
          0,
          0,
          0
        ]
      },
      "L1_N46": {
        "boxes": [
          0,
          0,
          0,
          0
        ]
      },
      "L1_N62": {
        "boxes": [
          0,
          0,
          0,
          0
        ]
      },
      "L1_N67": {
        "boxes": [
          5,
          5,
          14,
          14
        ]
      }
    },
    "9": {
      "L1_N22": {
        "boxes": [
          0,
          0,
          0,
          0
        ]
      },
      "L1_N24": {
        "boxes": [
          0,
          0,
          0,
          0
        ]
      },
      "L1_N27": {
        "boxes": [
          0,
          0,
          0,
          0
        ]
      },
      "L1_N50": {
        "boxes": [
          0,
          0,
          0,
          0
        ]
      },
      "L1_N55": {
        "boxes": [
          0,
          0,
          0,
          0
        ]
      }
    },
    "10": {
      "L1_N28": {
        "boxes": [
          0,
          0,
          0,
          0
        ]
      },
      "L1_N44": {
        "boxes": [
          0,
          0,
          0,
          0
        ]
      },
      "L1_N49": {
        "boxes": [
          0,
          0,
          0,
          0
        ]
      },
      "L1_N53": {
        "boxes": [
          0,
          0,
          0,
          0
        ]
      }
    },
    "11": {
      "L1_N36": {
        "boxes": [
          0,
          0,
          0,
          0
        ]
      },
      "L1_N37": {
        "boxes": [
          0,
          0,
          0,
          0
        ]
      },
      "L1_N38": {
        "boxes": [
          0,
          0,
          0,
          0
        ]
      },
      "L1_N39": {
        "boxes": [
          0,
          0,
          0,
          0
        ]
      },
      "L1_N40": {
        "boxes": [
          0,
          0,
          0,
          0
        ]
      },
      "L1_N45": {
        "boxes": [
          0,
          0,
          0,
          0
        ]
      },
      "L1_N68": {
        "boxes": [
          0,
          0,
          0,
          0
        ]
      },
      "L1_N69": {
        "boxes": [
          0,
          0,
          0,
          0
        ]
      }
    },
    "12": {
      "L1_N41": {
        "boxes": [
          0,
          0,
          0,
          0
        ]
      },
      "L1_N47": {
        "boxes": [
          0,
          0,
          0,
          0
        ]
      },
      "L1_N48": {
        "boxes": [
          0,
          0,
          0,
          0
        ]
      },
      "L1_N66": {
        "boxes": [
          0,
          0,
          0,
          0
        ]
      },
      "L1_N8": {
        "boxes": [
          0,
          0,
          0,
          0
        ]
      }
    },
    "13": {
      "L1_N58": {
        "boxes": [
          0,
          0,
          0,
          0
        ]
      },
      "L1_N6": {
        "boxes": [
          0,
          0,
          0,
          0
        ]
      },
      "L1_N65": {
        "boxes": [
          0,
          0,
          0,
          0
        ]
      },
      "L1_N77": {
        "boxes": [
          9,
          4,
          18,
          14
        ]
      }
    }
  },
  "level_2": {
    "0": {
      "L2_N0": {
        "boxes": [
          9,
          4,
          18,
          14
        ]
      },
      "L2_N10": {
        "boxes": [
          4,
          9,
          14,
          18
        ]
      },
      "L2_N11": {
        "boxes": [
          8,
          6,
          17,
          15
        ]
      },
      "L2_N12": {
        "boxes": [
          8,
          6,
          17,
          15
        ]
      },
      "L2_N13": {
        "boxes": [
          0,
          0,
          0,
          0
        ]
      },
      "L2_N2": {
        "boxes": [
          0,
          0,
          0,
          0
        ]
      },
      "L2_N3": {
        "boxes": [
          4,
          4,
          13,
          13
        ]
      }
    },
    "1": {
      "L2_N1": {
        "boxes": [
          4,
          9,
          14,
          18
        ]
      },
      "L2_N4": {
        "boxes": [
          0,
          0,
          0,
          0
        ]
      },
      "L2_N5": {
        "boxes": [
          9,
          4,
          18,
          14
        ]
      },
      "L2_N6": {
        "boxes": [
          9,
          4,
          18,
          14
        ]
      },
      "L2_N7": {
        "boxes": [
          4,
          4,
          13,
          13
        ]
      },
      "L2_N8": {
        "boxes": [
          0,
          0,
          0,
          0
        ]
      },
      "L2_N9": {
        "boxes": [
          9,
          4,
          18,
          14
        ]
      }
    }
  },
  "level_3": {
    "0": {
      "0": {
        "boxes": [
          7,
          5,
          16,
          14
        ]
      },
      "1": {
        "boxes": [
          8,
          4,
          17,
          14
        ]
      }
    }
  }
}