{
  "partition": {
    "index": 4853,
    "name": "jpeg_encoder.clknet_leaf_9_clk",
    "inbits": {
      "clknet_leaf_99_clk": [
        0
      ]
    },
    "outbits": {
      "clknet_leaf_9_clk": [
        0
      ]
    },
    "crossbits": {}
  },
  "gold_module": {
    "name": "gold.jpeg_encoder.clknet_leaf_9_clk",
    "internal": {},
    "unused": {},
    "cellcount": 1,
    "bitcount": 2
  },
  "gate_module": {
    "name": "gold.jpeg_encoder.clknet_leaf_9_clk",
    "internal": {},
    "unused": {},
    "cellcount": 1,
    "bitcount": 2
  }
}
